str_sim_scorer/__init__.py
str_sim_scorer/str_sim_scorer.py
str_sim_scorer/utils.py
str_sim_scorer-3.1.1.dist-info/METADATA
str_sim_scorer-3.1.1.dist-info/WHEEL
str_sim_scorer-3.1.1.dist-info/RECORD
