Metadata-Version: 2.1
Name: str_sim_scorer
Version: 3.1.1
Summary: 
Author: Devin McCabe
Author-email: dmccabe@broadinstitute.org
Requires-Python: >=3.9
Classifier: Programming Language :: Python :: 3
Classifier: Programming Language :: Python :: 3.9
Classifier: Programming Language :: Python :: 3.10
Classifier: Programming Language :: Python :: 3.11
Classifier: Programming Language :: Python :: 3.12
Classifier: Programming Language :: Python :: 3.13
Requires-Dist: numpy (>=1.26.3)
Requires-Dist: pandas (>=1.4)
Requires-Dist: scipy (>=1.12.0)
